runtests.py
querylanguage/__init__.py
querylanguage/exceptions.py
querylanguage/resolver.py
django_query_language-0.1.3.dist-info/METADATA
django_query_language-0.1.3.dist-info/WHEEL
django_query_language-0.1.3.dist-info/licenses/LICENSE
django_query_language-0.1.3.dist-info/RECORD
